odoo/addons/contract_sale_payment_mode/README.rst
odoo/addons/contract_sale_payment_mode/__init__.py
odoo/addons/contract_sale_payment_mode/__manifest__.py
odoo/addons/contract_sale_payment_mode/i18n/contract_sale_payment_mode.pot
odoo/addons/contract_sale_payment_mode/i18n/da.po
odoo/addons/contract_sale_payment_mode/i18n/es.po
odoo/addons/contract_sale_payment_mode/i18n/fr.po
odoo/addons/contract_sale_payment_mode/i18n/it.po
odoo/addons/contract_sale_payment_mode/i18n/pt.po
odoo/addons/contract_sale_payment_mode/i18n/pt_BR.po
odoo/addons/contract_sale_payment_mode/models/__init__.py
odoo/addons/contract_sale_payment_mode/models/res_company.py
odoo/addons/contract_sale_payment_mode/models/res_config_settings.py
odoo/addons/contract_sale_payment_mode/models/sale_order.py
odoo/addons/contract_sale_payment_mode/readme/CONTRIBUTORS.md
odoo/addons/contract_sale_payment_mode/readme/DESCRIPTION.md
odoo/addons/contract_sale_payment_mode/static/description/icon.png
odoo/addons/contract_sale_payment_mode/static/description/index.html
odoo/addons/contract_sale_payment_mode/tests/__init__.py
odoo/addons/contract_sale_payment_mode/tests/test_sale_order.py
odoo/addons/contract_sale_payment_mode/views/res_config_settings.xml
odoo/addons/contract_sale_payment_mode/views/sale_order.xml
odoo_addon_contract_sale_payment_mode-18.0.1.0.0.4.dist-info/METADATA
odoo_addon_contract_sale_payment_mode-18.0.1.0.0.4.dist-info/WHEEL
odoo_addon_contract_sale_payment_mode-18.0.1.0.0.4.dist-info/top_level.txt
odoo_addon_contract_sale_payment_mode-18.0.1.0.0.4.dist-info/RECORD
